[{"title":"/.git","link":"/.git","navs":null},{"title":"/.gitignore","link":"/.gitignore","navs":null},{"title":"/2019-02-02-fs-perf-collections.html","link":"/2019-02-02-fs-perf-collections.html","navs":null},{"title":"/2019-02-02-fs-perf-explorations.html","link":"/2019-02-02-fs-perf-explorations.html","navs":null},{"title":"/2019-04-06-fs-expecto-setup.html","link":"/2019-04-06-fs-expecto-setup.html","navs":null},{"title":"/2019-04-06-fs-test-clone..html","link":"/2019-04-06-fs-test-clone..html","navs":null},{"title":"/apps","link":"/apps","navs":null},{"title":"/assets","link":"/assets","navs":null},{"title":"/_apps","link":"/_apps","navs":null},{"title":"/_data","link":"/_data","navs":null},{"title":"/_posts","link":"/_posts","navs":null}]